pyquantumclifford/__init__.py
pyquantumclifford/juliapkg.json
pyquantumclifford/py.typed
pyquantumclifford-0.10.1.dist-info/WHEEL
pyquantumclifford-0.10.1.dist-info/METADATA
pyquantumclifford-0.10.1.dist-info/RECORD
