Metadata-Version: 2.3
Name: pyquantumclifford
Version: 0.10.1
Summary: Thin Python wrapper for the Julia library QuantumClifford.jl and QuantumClifford.ECC. Supports extremely fast Stabilizer state simulations, weakly non-Clifford dynamics, and generation of many modern quantum error correcting codes.
Author: Stefan Krastanov
Author-email: Stefan Krastanov <stefan@krastanov.org>
Requires-Dist: juliacall>=0.9.27
Requires-Dist: juliapkg>=0.1.13
Requires-Python: >=3.11
